setup.py
DPcalc/DPcalc.py
DPcalc/__init__.py
DPcalc.egg-info/PKG-INFO
DPcalc.egg-info/SOURCES.txt
DPcalc.egg-info/dependency_links.txt
DPcalc.egg-info/not-zip-safe
DPcalc.egg-info/top_level.txt