Metadata-Version: 2.1
Name: DPcalc
Version: 0.1
Summary: Calculatror that adds,substracts,multiplies,divides, and takes n root
Author: Deivydas Pagojus
